flask_transcrypt.py
flask_transcrypt-0.1.1.dist-info/LICENSE
flask_transcrypt-0.1.1.dist-info/METADATA
flask_transcrypt-0.1.1.dist-info/WHEEL
flask_transcrypt-0.1.1.dist-info/top_level.txt
flask_transcrypt-0.1.1.dist-info/RECORD
