Metadata-Version: 2.1
Name: flask-transcrypt
Version: 0.1.1
Summary: Flask extension to integrate Transcrypt
Home-page: https://github.com/codewithmpia/flask_transcrypt
Author: codewithmpia
Author-email: codewithmpia@gmail.com
Project-URL: Source, https://github.com/codewithmpia/flask_transcrypt
Project-URL: Tracker, https://github.com/codewithmpia/flask_transcrypt/issues
Project-URL: Author, https://github.com/codewithmpia
Classifier: Development Status :: 5 - Production/Stable
Classifier: Intended Audience :: Developers
Classifier: License :: OSI Approved :: MIT License
Classifier: Programming Language :: Python :: 3
Classifier: Framework :: Flask
License-File: LICENSE
Requires-Dist: Flask
Requires-Dist: transcrypt
